scenario/__init__.py
scenario/bindings/_core.so
scenario/bindings/_gazebo.so
scenario/bindings/core.py
scenario/bindings/gazebo.py
scenario/include/scenario/controllers/ComputedTorqueFixedBase.h
scenario/include/scenario/controllers/Controller.h
scenario/include/scenario/controllers/References.h
scenario/include/scenario/core/Joint.h
scenario/include/scenario/core/Link.h
scenario/include/scenario/core/Model.h
scenario/include/scenario/core/World.h
scenario/include/scenario/core/utils/Log.h
scenario/include/scenario/core/utils/signals.h
scenario/include/scenario/core/utils/utils.h
scenario/include/scenario/gazebo/GazeboEntity.h
scenario/include/scenario/gazebo/GazeboSimulator.h
scenario/include/scenario/gazebo/Joint.h
scenario/include/scenario/gazebo/Link.h
scenario/include/scenario/gazebo/Log.h
scenario/include/scenario/gazebo/Model.h
scenario/include/scenario/gazebo/World.h
scenario/include/scenario/gazebo/exceptions.h
scenario/include/scenario/gazebo/helpers.h
scenario/include/scenario/gazebo/utils.h
scenario/include/scenario/gazebo/components/BasePoseTarget.h
scenario/include/scenario/gazebo/components/BaseWorldAccelerationTarget.h
scenario/include/scenario/gazebo/components/BaseWorldVelocityTarget.h
scenario/include/scenario/gazebo/components/ExternalWorldWrenchCmdWithDuration.h
scenario/include/scenario/gazebo/components/HistoryOfAppliedJointForces.h
scenario/include/scenario/gazebo/components/JointAcceleration.h
scenario/include/scenario/gazebo/components/JointAccelerationTarget.h
scenario/include/scenario/gazebo/components/JointControlMode.h
scenario/include/scenario/gazebo/components/JointController.h
scenario/include/scenario/gazebo/components/JointControllerPeriod.h
scenario/include/scenario/gazebo/components/JointPID.h
scenario/include/scenario/gazebo/components/JointPositionTarget.h
scenario/include/scenario/gazebo/components/JointVelocityTarget.h
scenario/include/scenario/gazebo/components/SimulatedTime.h
scenario-1.3.1.dist-info/METADATA
scenario-1.3.1.dist-info/WHEEL
scenario-1.3.1.dist-info/top_level.txt
scenario-1.3.1.dist-info/RECORD
