Metadata-Version: 2.1
Name: scenario
Version: 1.3.1
Summary: SCENe interfAces for Robot Input/Output.
Home-page: https://github.com/robotology/gym-ignition/tree/master/scenario
Author: Diego Ferigo
Author-email: dgferigo@gmail.com
License: LGPL
Project-URL: Changelog, https://github.com/robotology/gym-ignition/releases
Project-URL: Tracker, https://github.com/robotology/gym-ignition/issues
Project-URL: Documentation, https://robotology.github.io/gym-ignition
Project-URL: Source, https://github.com/robotology/gym-ignition/tree/master/scenario
Keywords: robotics,gazebo,ignition,simulation,physics,multibody,dynamics,physics simulation,middleware,real-time
Platform: any
Classifier: Development Status :: 5 - Production/Stable
Classifier: Operating System :: POSIX :: Linux
Classifier: Topic :: Games/Entertainment :: Simulation
Classifier: Topic :: Scientific/Engineering :: Artificial Intelligence
Classifier: Topic :: Scientific/Engineering :: Physics
Classifier: Topic :: Software Development
Classifier: Framework :: Robot Framework
Classifier: Intended Audience :: Developers
Classifier: Intended Audience :: Science/Research
Classifier: Programming Language :: C++
Classifier: Programming Language :: Python :: 3.8
Classifier: Programming Language :: Python :: 3.9
Classifier: Programming Language :: Python :: 3 :: Only
Classifier: Programming Language :: Python :: Implementation :: CPython
Classifier: License :: OSI Approved :: GNU Lesser General Public License v2 or later (LGPLv2+)
Requires-Python: >=3.8
Requires-Dist: packaging
